french_highschool/__init__.py
french_highschool/admin.py
french_highschool/apps.py
french_highschool/constants.py
french_highschool/models.py
french_highschool/fixtures/high_school.json
french_highschool/migrations/0001_initial.py
french_highschool/migrations/0002_alter_school_options.py
french_highschool/migrations/__init__.py
django_french_highschool-0.17.0.dist-info/LICENSE
django_french_highschool-0.17.0.dist-info/METADATA
django_french_highschool-0.17.0.dist-info/WHEEL
django_french_highschool-0.17.0.dist-info/top_level.txt
django_french_highschool-0.17.0.dist-info/RECORD
